fesdql/__init__.py
fesdql/_alchemy.py
fesdql/_cachelru.py
fesdql/_err_msg.py
fesdql/_fields.py
fesdql/async_mongo.py
fesdql/err.py
fesdql/query.py
fesdql/sync_mongo.py
fesdql/utils.py
fesdql-1.1.3.dist-info/LICENSE
fesdql-1.1.3.dist-info/METADATA
fesdql-1.1.3.dist-info/WHEEL
fesdql-1.1.3.dist-info/top_level.txt
fesdql-1.1.3.dist-info/RECORD
