Metadata-Version: 2.1
Name: fesdql
Version: 1.1.3
Summary: MongoDB同步异步基础封装库
Home-page: https://github.com/tinybees/fesdql
Author: TinyBees
Author-email: a598824322@qq.com
License: MIT
Keywords: mongo,asyncio,sync,crud,session
Platform: UNKNOWN
Classifier: Development Status :: 5 - Production/Stable
Classifier: Intended Audience :: Developers
Classifier: License :: OSI Approved :: MIT License
Classifier: Natural Language :: Chinese (Simplified)
Classifier: Operating System :: POSIX :: Linux
Classifier: Operating System :: Microsoft :: Windows
Classifier: Operating System :: MacOS :: MacOS X
Classifier: Topic :: Software Development :: Libraries :: Python Modules
Classifier: Topic :: Utilities
Classifier: Programming Language :: Python
Classifier: Programming Language :: Python :: 3.6
Classifier: Programming Language :: Python :: 3.7
Classifier: Programming Language :: Python :: 3.8
Requires-Python: >=3.6
Requires-Dist: aelog (<=1.0.9,>=1.0.6)
Requires-Dist: marshmallow (<=3.14.1,>=3.0.1)
Provides-Extra: async
Requires-Dist: motor (<=2.5.1,>=2.1.0) ; extra == 'async'
Requires-Dist: pymongo (<=3.13.0,>=3.10.1) ; extra == 'async'
Provides-Extra: sync
Requires-Dist: pymongo (<=4.1.1,>=3.10.1) ; extra == 'sync'
